{
  "trades": [
    {
      "ticker": "FORM",
      "side": "buy",
      "date": "2026-04-10",
      "price": 123.8,
      "qty": 161.0,
      "cost_basis": 19931.8,
      "score_at_entry": 9.8,
      "reason": "Score \u2265 9.5",
      "alpaca_order_id": "132208f8-2100-473b-9b7b-1f8f3a45fd19"
    },
    {
      "ticker": "IRDM",
      "side": "buy",
      "date": "2026-04-10",
      "price": 34.2,
      "qty": 584.0,
      "cost_basis": 19972.8,
      "score_at_entry": 9.8,
      "reason": "Score \u2265 9.5",
      "alpaca_order_id": "95273f95-62b4-4c98-9eca-1af83ec6a38b"
    },
    {
      "ticker": "VIAV",
      "side": "buy",
      "date": "2026-04-10",
      "price": 41.79,
      "qty": 478.0,
      "cost_basis": 19975.62,
      "score_at_entry": 9.8,
      "reason": "Score \u2265 9.5",
      "alpaca_order_id": "cc19ff91-fa49-4c6e-9234-40b211611978"
    },
    {
      "ticker": "AEHR",
      "side": "buy",
      "date": "2026-04-15",
      "price": 73.22,
      "qty": 278.0,
      "cost_basis": 20355.16,
      "score_at_entry": 9.2,
      "reason": "Score \u2265 8.5 + 3d persist",
      "alpaca_order_id": "bb2434e0-1054-4dc1-a131-206f8da60cdd"
    },
    {
      "ticker": "WDC",
      "side": "buy",
      "date": "2026-04-15",
      "price": 365.0,
      "qty": 53.0,
      "cost_basis": 19345.0,
      "score_at_entry": 8.8,
      "reason": "Score \u2265 8.5 + 3d persist",
      "alpaca_order_id": "2c4cf2db-408b-4ca7-aad6-54623b66f58d"
    }
  ]
}